{"name":"open  browser","id":"open-browser;open--browser","testSteps":[{"number":1,"description":"Given the user enter the  page","duration":7810,"startTime":"2023-09-16T14:30:06.108-05:00[America/Bogota]","result":"SUCCESS","precondition":false,"level":0}],"userStory":{"id":"open-browser","storyName":"Open Browser","path":"openBrowser.feature","narrative":"  As user open browser in the main page","type":"feature"},"featureTag":{"name":"Open Browser","type":"feature","displayName":"Open Browser"},"title":"open  browser","description":"","tags":[{"name":"Open Browser","type":"feature","displayName":"Open Browser"}],"startTime":"2023-09-16T14:30:05.990-05:00[America/Bogota]","duration":8588,"projectKey":"","isManualTestingUpToDate":false,"manual":false,"testSource":"Cucumber","result":"SUCCESS"}